outliers_navkiran.py
outliers_navkiran_cli.py
outliers_navkiran-1.1.0.dist-info/LICENSE
outliers_navkiran-1.1.0.dist-info/METADATA
outliers_navkiran-1.1.0.dist-info/WHEEL
outliers_navkiran-1.1.0.dist-info/entry_points.txt
outliers_navkiran-1.1.0.dist-info/top_level.txt
outliers_navkiran-1.1.0.dist-info/RECORD
